google_news_api/__init__.py
google_news_api/client.py
google_news_api/config.py
google_news_api/exceptions.py
google_news_api/logging.py
google_news_api/utils.py
google_news_api-0.0.6.dist-info/LICENSE
google_news_api-0.0.6.dist-info/METADATA
google_news_api-0.0.6.dist-info/WHEEL
google_news_api-0.0.6.dist-info/RECORD
