Metadata-Version: 2.3
Name: google-news-api
Version: 0.0.6
Summary: 
Author: Paolo Mazza
Author-email: mazzapaolo2019@gmail.com
Requires-Python: >=3.9
Classifier: Programming Language :: Python :: 3
Classifier: Programming Language :: Python :: 3.9
Classifier: Programming Language :: Python :: 3.10
Classifier: Programming Language :: Python :: 3.11
Classifier: Programming Language :: Python :: 3.12
Classifier: Programming Language :: Python :: 3.13
Requires-Dist: feedparser (>=6.0.11,<7.0.0)
Requires-Dist: httpx (>=0.28.1,<0.29.0)
Requires-Dist: selectolax (>=0.3.29,<0.4.0)
Requires-Dist: tqdm (>=4.67.1,<5.0.0)
